TestingCode/fifo.v
`timescale 1ns / 1ps
module SyncFIFO(clk, rst, full, wEn, dIn, empty, rEn, dOut, faultEn);
parameter BITWIDTH = 5;
parameter DEPTH = 4;
input clk, rst, wEn, rEn, faultEn;
wire wEn1 =  wEn;
input [BITWIDTH-1:0] dIn;
output full, empty;
output reg [BITWIDTH-1:0] dOut;
reg [BITWIDTH-1:0] vars    [0:2**(DEPTH)-1];
reg [BITWIDTH-1:0] varsNxt [0:2**(DEPTH)-1]; //to avoid latches
integer ii;
reg [DEPTH:0] rPtr, rPtrNxt, wPtr, wPtrNxt, wPtrPrev; //the extra bit is used as a flag to differentiate between full and empty
always@(posedge clk)begin
	rPtr 		<= #1 rPtrNxt;
	wPtr 		<= #1 wPtrNxt;
	wPtrPrev <= #1 wPtr;
	for (ii = 0; ii < 2**(DEPTH); ii = ii+1) begin //to avoid latches
		vars[ii] <= #1 varsNxt[ii];
	end
end

always@* begin
	for (ii = 0; ii < 2**(DEPTH); ii = ii+1) begin //to avoid latches
		varsNxt[ii] = vars[ii];
	end
	dOut = vars[rPtr[DEPTH-1:0]][BITWIDTH-1:0];
	rPtrNxt  = rPtr;
	wPtrNxt  = wPtr;
	if(rst) begin
		rPtrNxt = 0;
		wPtrNxt = 0;
		dOut 	  = 0;
		for (ii = 0; ii < 2**(DEPTH); ii = ii+1) begin
			varsNxt[ii] = 0;
		end
	end else begin		
		//normal read
		if(!empty &rEn)begin 
			rPtrNxt = rPtr + 1;
		end
		//normal write, if (empty & rEn & wEn) we can output dIn directly, no need to write in the memory
		// if its full but both rEn and wEn are 1, we can read and write
		if(!full & wEn1 &!(empty & rEn & wEn1) | (full & rEn & wEn1)) begin 
			varsNxt[wPtr[DEPTH-1:0]] = dIn;
			wPtrNxt = wPtr + 1;
		end		
		//if it's empty but both rEn and wEn are 1, we can output dIn, no need to write in memory
		if(empty & rEn & wEn1) begin 
			dOut = dIn;
		end
	end
end

assign empty =  (wPtr == rPtr) ? 1'b1: 1'b0;
assign full  =  ((wPtr[DEPTH-1:0] == rPtr[DEPTH-1:0]) & (wPtr[DEPTH] != rPtr[DEPTH]))   ? 1'b1: 1'b0;

endmodule

TestingCode/FIFO_tb.v
`timescale 1ns / 1ps
`define BITWIDTH 6
`define DEPTH 4
`define NUMREADS 500
module FIFO_tb;

   reg clk, rst;
   
   initial begin
      clk = 0;
      forever
        #5 clk = ~clk;
   end

   initial begin
      $dumpfile("FIFO.vcd");
      $dumpvars(2, FIFO_tb);
      rst <= #1 1;
      repeat(2) @(posedge clk);
      rst <= #1 0;
   end

   // Control simulation termination from a single command center:
   initial begin
      fork
         forever begin
            @(checker.numRead);
            if(checker.numRead%100 == 0)
	      $display("numRead = ", checker.numRead);
            if(checker.numRead == `NUMREADS) begin
               @(posedge clk);
               if(checker.errorCnt == 0)
                 $display("pass ======> No errors. Congrats!");
               $finish;
            end
         end
         forever begin
            @(checker.errorCnt);
            if(checker.errorCnt == 5) begin
               $display("fail ======> Stopped after 5 errors!");
               $finish;
	    end
         end
      join
   end

   wire [`BITWIDTH-1:0] dIn, dOut;
   
   // note that we can always read
   // and rEn=1 in fact indicates pop
   // rather than read.
   SyncFIFO #(`BITWIDTH, `DEPTH) DUT(.clk(clk), .rst(rst),
                             .full(full), .wEn(wEn), .dIn(dIn),
                             .empty(empty), .rEn(rEn), .dOut(dOut));

   driver driver(.clk(clk), .rst(rst),
                 .full(full), .wEn(wEn), .dIn(dIn),
                 .rEn(rEn));
   
   checker checker(.clk(clk), .rst(rst),
                   .empty(empty), .rEn(rEn), .dOut(dOut), .wEn(wEn));

endmodule // oneSlotFIFO_tb

module driver(clk, rst, full, wEn, dIn, rEn);
   input clk, rst;
   input full;
   output wEn;
   output [`BITWIDTH-1:0] dIn;
   input                  rEn;

   reg                    wEn;
   reg [`BITWIDTH-1:0]    dIn;

   integer                waitLen, burstLen;
   reg [3:0]              len;

   initial begin
      dIn = 0;
      wEn = 0;
      @(negedge rst);

      forever begin
         len = $random;
         repeat(len) @(posedge clk);

         len = $random%(2**`DEPTH);
         burstWriteIfYouCan(len);
      end
   end
   
   task burstWriteIfYouCan;
      input [3:0]         burstWrLen;
      begin
         repeat(burstWrLen) begin
            // check for the corner case of wEn=1 when full=1 but rEn=1
            wait(~full | rEn);

            wEn = 1;
            @(posedge clk);
            wEn <= #1 0;
            dIn <= #1 (dIn +1)%(1<<`BITWIDTH);

            // wait for full signal to react
            @(negedge clk);
         end
      end
   endtask // burstWriteIfYouCan

endmodule // driver

module checker(clk, rst, empty, rEn, dOut, wEn);
   input clk, rst;
   input empty, wEn;
   output rEn;
   input [`BITWIDTH-1:0] dOut;

   reg                    rEn;
   reg [`BITWIDTH-1:0]    dOutRef;

   reg [3:0]              len;

   initial begin
      dOutRef = 0;
      rEn = 0;
      @(negedge rst);
      forever begin
         len = $random;
         repeat(len) @(posedge clk);

         len = $random;
         burstReadIfYouCan(len);
      end
   end

   integer numRead=0, errorCnt=0;

   task burstReadIfYouCan;
      input [3:0] burstRdLen;
      begin
         repeat(burstRdLen) begin
				//check for the corner case when empty = 1, wEn = 1, and rEn = 1, it should output dIn
            wait(~empty | wEn);
            numRead <= #1 numRead +1;                                   
            rEn = 1;
            #2; // wait just in case dOut changes too early
            
            if(dOut !== dOutRef) begin
               $display("======> Error at time=%0d: dOut=%d vs dOutRef=%d",
                        $time, dOut, dOutRef);
               errorCnt = errorCnt +1;
            end

            @(posedge clk);
            rEn <= #1 0;
            dOutRef <= #1 (dOutRef +1)%(1<<`BITWIDTH);

            // wait for empty signal to react
            @(negedge clk);
         end
      end
   endtask

endmodule // checker

TestingCode/FIFO.vcd
$date
	Tue Mar 14 11:22:52 2023
$end
$version
	Icarus Verilog
$end
$timescale
	1ps
$end
$scope module FIFO_tb $end
$var wire 1 ! wEn $end
$var wire 1 " rEn $end
$var wire 1 # full $end
$var wire 1 $ empty $end
$var wire 6 % dOut [5:0] $end
$var wire 6 & dIn [5:0] $end
$var reg 1 ' clk $end
$var reg 1 ( rst $end
$scope module DUT $end
$var wire 1 ' clk $end
$var wire 1 ) faultEn $end
$var wire 1 ( rst $end
$var wire 1 * wEn1 $end
$var wire 1 ! wEn $end
$var wire 1 " rEn $end
$var wire 1 # full $end
$var wire 1 $ empty $end
$var wire 6 + dIn [5:0] $end
$var reg 6 , dOut [5:0] $end
$var reg 5 - rPtr [4:0] $end
$var reg 5 . rPtrNxt [4:0] $end
$var reg 5 / wPtr [4:0] $end
$var reg 5 0 wPtrNxt [4:0] $end
$var reg 5 1 wPtrPrev [4:0] $end
$var integer 32 2 ii [31:0] $end
$upscope $end
$scope module checker $end
$var wire 1 ' clk $end
$var wire 6 3 dOut [5:0] $end
$var wire 1 $ empty $end
$var wire 1 ( rst $end
$var wire 1 ! wEn $end
$var reg 6 4 dOutRef [5:0] $end
$var reg 4 5 len [3:0] $end
$var reg 1 " rEn $end
$var integer 32 6 errorCnt [31:0] $end
$var integer 32 7 numRead [31:0] $end
$upscope $end
$scope module driver $end
$var wire 1 ' clk $end
$var wire 1 # full $end
$var wire 1 " rEn $end
$var wire 1 ( rst $end
$var reg 6 8 dIn [5:0] $end
$var reg 4 9 len [3:0] $end
$var reg 1 ! wEn $end
$upscope $end
$upscope $end
$enddefinitions $end
#0
$dumpvars
bx 9
b0 8
b0 7
b0 6
bx 5
b0 4
bx 3
b10000 2
bx 1
bx 0
bx /
bx .
bx -
bx ,
b0 +
0*
z)
x(
0'
b0 &
bx %
x$
x#
0"
0!
$end
#1000
b0 %
b0 ,
b0 3
b0 0
b0 .
b10000 2
1(
#5000
b0 0
b0 .
b0 %
b0 ,
b0 3
b10000 2
1'
#6000
0#
1$
b10000 2
b0 /
b0 -
#10000
0'
#15000
b10000 2
1'
#16000
b10000 2
b1 9
b100 5
0(
b0 1
#20000
0'
#25000
b1 0
1*
1!
b10000 2
b1001 9
1'
#30000
0'
#35000
b1 0
b10000 2
1'
#36000
0$
b10000 2
b1 /
b1 &
b1 +
b1 8
0*
0!
#40000
b10 0
b10000 2
1*
1!
0'
#45000
b10 0
b10000 2
1'
#46000
b10000 2
b1 1
b10 /
b10 &
b10 +
b10 8
0*
0!
#50000
b11 0
b10000 2
1*
1!
0'
#55000
b1 .
b11 0
1"
b11 5
b10000 2
1'
#56000
b1 .
b10000 2
b1 7
b10 1
b11 /
b11 &
b11 +
b11 8
0*
0!
#60000
b100 0
b1 .
b10000 2
1*
1!
0'
#65000
b100 0
b1 .
b10000 2
1'
#66000
b1 %
b1 ,
b1 3
b10000 2
b11 1
b100 /
b1 -
b1 4
0"
b100 &
b100 +
b100 8
0*
0!
#70000
b101 0
b10 .
b10000 2
1*
1!
1"
0'
#71000
b10 7
#75000
b101 0
b10 .
b10000 2
1'
#76000
b10 %
b10 ,
b10 3
b10000 2
b100 1
b101 /
b10 -
b101 &
b101 +
b101 8
0*
0!
b10 4
0"
#80000
b110 0
b11 .
b10000 2
1"
1*
1!
0'
#81000
b11 7
#85000
b110 0
b11 .
b10000 2
1'
#86000
b11 %
b11 ,
b11 3
b10000 2
b101 1
b110 /
b11 -
b110 &
b110 +
b110 8
0*
0!
b11 4
0"
#90000
b111 0
b10000 2
b1101 5
1*
1!
0'
#95000
b111 0
b10000 2
1'
#96000
b10000 2
b110 1
b111 /
b111 &
b111 +
b111 8
0*
0!
#100000
b1000 0
b10000 2
1*
1!
0'
#105000
b1000 0
b10000 2
1'
#106000
b10000 2
b111 1
b1000 /
b1000 &
b1000 +
b1000 8
0*
0!
#110000
b1001 0
b10000 2
1*
1!
0'
#115000
b1001 0
b10000 2
1'
#116000
b10000 2
b1000 1
b1001 /
b1001 &
b1001 +
b1001 8
0*
0!
#120000
b1101 9
0'
#125000
b10000 2
1'
#126000
b1001 1
#130000
0'
#135000
b10000 2
1'
#140000
0'
#145000
b10000 2
1'
#150000
0'
#155000
b10000 2
1'
#160000
0'
#165000
b10000 2
1'
#170000
0'
#175000
b10000 2
1'
#180000
0'
#185000
b10000 2
1'
#190000
0'
#195000
b10000 2
1'
#200000
0'
#205000
b10000 2
1'
#210000
0'
#215000
b100 .
1"
b10000 2
b101 5
1'
#216000
b100 7
#220000
0'
#225000
b100 .
b10000 2
1'
#226000
b100 %
b100 ,
b100 3
b10000 2
b100 -
b100 4
0"
#230000
b101 .
b10000 2
1"
0'
#231000
b101 7
#235000
b101 .
b10000 2
1'
#236000
b101 %
b101 ,
b101 3
b10000 2
b101 -
b101 4
0"
#240000
b110 .
b10000 2
1"
0'
#241000
b110 7
#245000
b1010 0
b110 .
1*
1!
b10000 2
b10 9
1'
#246000
b1010 0
b110 %
b110 ,
b110 3
b10000 2
b110 -
b110 4
0"
#250000
b111 .
b1010 0
b10000 2
1"
0'
#251000
b111 7
#255000
b1010 0
b111 .
b10000 2
1'
#256000
b111 %
b111 ,
b111 3
b10000 2
b1010 /
b111 -
b1010 &
b1010 +
b1010 8
0*
0!
b111 4
0"
#260000
b1011 0
b1000 .
b10000 2
1"
1*
1!
0'
#261000
b1000 7
#265000
b1011 0
b1000 .
b10000 2
1'
#266000
b1000 %
b1000 ,
b1000 3
b10000 2
b1010 1
b1011 /
b1000 -
b1011 &
b1011 +
b1011 8
0*
0!
b1000 4
0"
#270000
b1101 9
b1 5
0'
#275000
b1001 .
1"
b10000 2
b110 5
1'
#276000
b1001 7
b1011 1
#280000
0'
#285000
b1001 .
b10000 2
1'
#286000
b1001 %
b1001 ,
b1001 3
b10000 2
b1001 -
b1001 4
0"
#290000
b1010 .
b10000 2
1"
0'
#291000
b1010 7
#295000
b1010 .
b10000 2
1'
#296000
b1010 %
b1010 ,
b1010 3
b10000 2
b1010 -
b1010 4
0"
#300000
b1011 .
b10000 2
1"
0'
#301000
b1011 7
#305000
b1011 .
b10000 2
1'
#306000
1$
b0 %
b0 ,
b0 3
b10000 2
b1011 -
b1011 4
0"
#310000
0'
#315000
b10000 2
1'
#320000
0'
#325000
b10000 2
1'
#330000
0'
#335000
b10000 2
1'
#340000
0'
#345000
b10000 2
1'
#350000
0'
#355000
b10000 2
1'
#360000
0'
#365000
b10000 2
1'
#370000
0'
#375000
b10000 2
1'
#380000
0'
#385000
b10000 2
1'
#390000
0'
#395000
b1011 %
b1011 ,
b1011 3
1"
b1011 0
1*
1!
b10000 2
1'
#396000
b1100 7
#400000
0'
#405000
b1011 %
b1011 ,
b1011 3
b10000 2
1'
#406000
b0 %
b0 ,
b0 3
b10000 2
b1100 &
b1100 +
b1100 8
0*
0!
b1100 4
0"
#410000
b1100 %
b1100 ,
b1100 3
b10000 2
1"
1*
1!
0'
#411000
b1101 7
#415000
b1100 %
b1100 ,
b1100 3
b10000 2
1'
#416000
b0 %
b0 ,
b0 3
b10000 2
b1101 &
b1101 +
b1101 8
0*
0!
b1101 4
0"
#420000
b1101 %
b1101 ,
b1101 3
b10000 2
1"
1*
1!
0'
#421000
b1110 7
#425000
b1101 %
b1101 ,
b1101 3
b10000 2
1'
#426000
b0 %
b0 ,
b0 3
b10000 2
b1110 &
b1110 +
b1110 8
0*
0!
b1110 4
0"
#430000
b1100 0
b10000 2
b1101 5
1*
1!
0'
#435000
b1100 0
b10000 2
1'
#436000
0$
b1110 %
b1110 ,
b1110 3
b10000 2
b1100 /
b1111 &
b1111 +
b1111 8
0*
0!
#440000
b1101 0
b10000 2
1*
1!
0'
#445000
b1101 0
b10000 2
1'
#446000
b10000 2
b1100 1
b1101 /
b10000 &
b10000 +
b10000 8
0*
0!
#450000
b1110 0
b10000 2
1*
1!
0'
#455000
b1110 0
b10000 2
1'
#456000
b10000 2
b1101 1
b1110 /
b10001 &
b10001 +
b10001 8
0*
0!
#460000
b1111 0
b10000 2
1*
1!
0'
#465000
b1111 0
b10000 2
1'
#466000
b10000 2
b1110 1
b1111 /
b10010 &
b10010 +
b10010 8
0*
0!
#470000
b10000 0
b10000 2
1*
1!
0'
#475000
b10000 0
b10000 2
1'
#476000
b10000 2
b1111 1
b10000 /
b10011 &
b10011 +
b10011 8
0*
0!
#480000
b10001 0
b10000 2
1*
1!
0'
#485000
b10001 0
b10000 2
1'
#486000
b10000 2
b10000 1
b10001 /
b10100 &
b10100 +
b10100 8
0*
0!
#490000
b10010 0
b10000 2
1*
1!
0'
#495000
b10010 0
b10000 2
1'
#496000
b10000 2
b10001 1
b10010 /
b10101 &
b10101 +
b10101 8
0*
0!
#500000
b10011 0
b10000 2
1*
1!
0'
#505000
b10011 0
b10000 2
1'
#506000
b10000 2
b10010 1
b10011 /
b10110 &
b10110 +
b10110 8
0*
0!
#510000
b10100 0
b10000 2
1*
1!
0'
#515000
b10100 0
b10000 2
1'
#516000
b10000 2
b10011 1
b10100 /
b10111 &
b10111 +
b10111 8
0*
0!
#520000
b10101 0
b10000 2
1*
1!
0'
#525000
b10101 0
b10000 2
1'
#526000
b10000 2
b10100 1
b10101 /
b11000 &
b11000 +
b11000 8
0*
0!
#530000
b1100 9
0'
#535000
b10000 2
1'
#536000
b10101 1
#540000
0'
#545000
b10000 2
1'
#550000
0'
#555000
b1100 .
1"
b10000 2
b1001 5
1'
#556000
b1111 7
#560000
0'
#565000
b1100 .
b10000 2
1'
#566000
b1111 %
b1111 ,
b1111 3
b10000 2
b1100 -
b1111 4
0"
#570000
b1101 .
b10000 2
1"
0'
#571000
b10000 7
#575000
b1101 .
b10000 2
1'
#576000
b10000 %
b10000 ,
b10000 3
b10000 2
b1101 -
b10000 4
0"
#580000
b1110 .
b10000 2
1"
0'
#581000
b10001 7
#585000
b1110 .
b10000 2
1'
#586000
b10001 %
b10001 ,
b10001 3
b10000 2
b1110 -
b10001 4
0"
#590000
b1111 .
b10000 2
1"
0'
#591000
b10010 7
#595000
b1111 .
b10000 2
1'
#596000
b10010 %
b10010 ,
b10010 3
b10000 2
b1111 -
b10010 4
0"
#600000
b10000 .
b10000 2
1"
0'
#601000
b10011 7
#605000
b10000 .
b10000 2
1'
#606000
b10011 %
b10011 ,
b10011 3
b10000 2
b10000 -
b10011 4
0"
#610000
b10001 .
b10000 2
1"
0'
#611000
b10100 7
#615000
b10001 .
b10000 2
1'
#616000
b10100 %
b10100 ,
b10100 3
b10000 2
b10001 -
b10100 4
0"
#620000
b10010 .
b10000 2
1"
0'
#621000
b10101 7
#625000
b10010 .
b10000 2
1'
#626000
b10101 %
b10101 ,
b10101 3
b10000 2
b10010 -
b10101 4
0"
#630000
b10011 .
b10000 2
1"
0'
#631000
b10110 7
#635000
b10011 .
b10000 2
1'
#636000
b10110 %
b10110 ,
b10110 3
b10000 2
b10011 -
b10110 4
0"
#640000
b10100 .
b10000 2
1"
0'
#641000
b10111 7
#645000
b10110 0
b10100 .
1*
1!
b110 9
b10000 2
1'
#646000
b10110 0
b10111 %
b10111 ,
b10111 3
b10000 2
b10100 -
b10111 4
0"
#650000
b101 5
0'
#655000
b10110 0
b10000 2
1'
#656000
b10000 2
b10110 /
b11001 &
b11001 +
b11001 8
0*
0!
#660000
b10111 0
b10000 2
1*
1!
0'
#665000
b10111 0
b10000 2
1'
#666000
b10000 2
b10110 1
b10111 /
b11010 &
b11010 +
b11010 8
0*
0!
#670000
b11000 0
b10000 2
1*
1!
0'
#675000
b11000 0
b10000 2
1'
#676000
b10000 2
b10111 1
b11000 /
b11011 &
b11011 +
b11011 8
0*
0!
#680000
b11001 0
b10000 2
1*
1!
0'
#685000
b11001 0
b10000 2
1'
#686000
b10000 2
b11000 1
b11001 /
b11100 &
b11100 +
b11100 8
0*
0!
#690000
b11010 0
b10000 2
1*
1!
0'
#695000
b10101 .
b11010 0
1"
b10000 2
b1010 5
1'
#696000
b10101 .
b10000 2
b11000 7
b11001 1
b11010 /
b11101 &
b11101 +
b11101 8
0*
0!
#700000
b11011 0
b10101 .
b10000 2
1*
1!
0'
#705000
b11011 0
b10101 .
b10000 2
1'
#706000
b11000 %
b11000 ,
b11000 3
b10000 2
b11010 1
b11011 /
b10101 -
b11000 4
0"
b11110 &
b11110 +
b11110 8
0*
0!
#710000
b10110 .
b10000 2
b101 9
1"
0'
#711000
b11001 7
#715000
b10110 .
b10000 2
1'
#716000
b11001 %
b11001 ,
b11001 3
b10000 2
b11011 1
b10110 -
b11001 4
0"
#720000
b10111 .
b10000 2
1"
0'
#721000
b11010 7
#725000
b10111 .
b10000 2
1'
#726000
b11010 %
b11010 ,
b11010 3
b10000 2
b10111 -
b11010 4
0"
#730000
b11000 .
b10000 2
1"
0'
#731000
b11011 7
#735000
b11000 .
b10000 2
1'
#736000
b11011 %
b11011 ,
b11011 3
b10000 2
b11000 -
b11011 4
0"
#740000
b11001 .
b10000 2
1"
0'
#741000
b11100 7
#745000
b11001 .
b10000 2
1'
#746000
b11100 %
b11100 ,
b11100 3
b10000 2
b11001 -
b11100 4
0"
#750000
b11010 .
b10000 2
1"
0'
#751000
b11101 7
#755000
b11100 0
b11010 .
1*
1!
b10000 2
b111 9
1'
#756000
b11100 0
b11101 %
b11101 ,
b11101 3
b10000 2
b11010 -
b11101 4
0"
#760000
b11011 .
b11100 0
b10000 2
1"
0'
#761000
b11110 7
#765000
b11100 0
b11011 .
b10000 2
1'
#766000
b11110 %
b11110 ,
b11110 3
b10000 2
b11100 /
b11011 -
b11111 &
b11111 +
b11111 8
0*
0!
b11110 4
0"
#770000
b11101 0
b11100 .
b10000 2
1"
1*
1!
0'
#771000
b11111 7
#775000
b11101 0
b11100 .
b10000 2
1'
#776000
b11111 %
b11111 ,
b11111 3
b10000 2
b11100 1
b11101 /
b11100 -
b100000 &
b100000 +
b100000 8
0*
0!
b11111 4
0"
#780000
b11110 0
b11101 .
b10000 2
1"
1*
1!
0'
#781000
b100000 7
#785000
b11110 0
b11101 .
b10000 2
1'
#786000
b100000 %
b100000 ,
b100000 3
b10000 2
b11101 1
b11110 /
b11101 -
b100001 &
b100001 +
b100001 8
0*
0!
b100000 4
0"
#790000
b11111 0
b11110 .
b10000 2
1"
1*
1!
0'
#791000
b100001 7
#795000
b11111 0
b11110 .
b10000 2
1'
#796000
b100001 %
b100001 ,
b100001 3
b10000 2
b11110 1
b11111 /
b11110 -
b100010 &
b100010 +
b100010 8
0*
0!
b100001 4
0"
#800000
b0 0
b10000 2
b10 5
1*
1!
0'
#805000
b0 0
b10000 2
1'
#806000
b10000 2
b11111 1
b0 /
b100011 &
b100011 +
b100011 8
0*
0!
#810000
b1 0
b10000 2
1*
1!
0'
#815000
b11111 .
b1 0
1"
b1111 5
b10000 2
1'
#816000
b11111 .
b10000 2
b100010 7
b0 1
b1 /
b100100 &
b100100 +
b100100 8
0*
0!
#820000
b10 0
b11111 .
b10000 2
1*
1!
0'
#825000
b10 0
b11111 .
b10000 2
1'
#826000
b100010 %
b100010 ,
b100010 3
b10000 2
b1 1
b10 /
b11111 -
b100010 4
0"
b100101 &
b100101 +
b100101 8
0*
0!
#830000
b0 .
b10000 2
b10 9
1"
0'
#831000
b100011 7
#835000
b0 .
b10000 2
1'
#836000
b100011 %
b100011 ,
b100011 3
b10000 2
b10 1
b0 -
b100011 4
0"
#840000
b1 .
b10000 2
1"
0'
#841000
b100100 7
#845000
b11 0
b1 .
1*
1!
b1110 9
b10000 2
1'
#846000
b11 0
b100100 %
b100100 ,
b100100 3
b10000 2
b1 -
b100100 4
0"
#850000
b10 .
b11 0
b10000 2
1"
0'
#851000
b100101 7
#855000
b11 0
b10 .
b10000 2
1'
#856000
b100101 %
b100101 ,
b100101 3
b10000 2
b11 /
b10 -
b100110 &
b100110 +
b100110 8
0*
0!
b100101 4
0"
#860000
b100 0
b11 .
b10000 2
1"
1*
1!
0'
#861000
b100110 7
#865000
b100 0
b11 .
b10000 2
1'
#866000
b100110 %
b100110 ,
b100110 3
b10000 2
b11 1
b100 /
b11 -
b100111 &
b100111 +
b100111 8
0*
0!
b100110 4
0"
#870000
b101 0
b100 .
b10000 2
1"
1*
1!
0'
#871000
b100111 7
#875000
b101 0
b100 .
b10000 2
1'
#876000
b100111 %
b100111 ,
b100111 3
b10000 2
b100 1
b101 /
b100 -
b101000 &
b101000 +
b101000 8
0*
0!
b100111 4
0"
#880000
b110 0
b101 .
b10000 2
1"
1*
1!
0'
#881000
b101000 7
#885000
b110 0
b101 .
b10000 2
1'
#886000
b101000 %
b101000 ,
b101000 3
b10000 2
b101 1
b110 /
b101 -
b101001 &
b101001 +
b101001 8
0*
0!
b101000 4
0"
#890000
b111 0
b110 .
b10000 2
1"
1*
1!
0'
#891000
b101001 7
#895000
b111 0
b110 .
b10000 2
1'
#896000
b101001 %
b101001 ,
b101001 3
b10000 2
b110 1
b111 /
b110 -
b101010 &
b101010 +
b101010 8
0*
0!
b101001 4
0"
#900000
b1000 0
b111 .
b10000 2
1"
1*
1!
0'
#901000
b101010 7
#905000
b1000 0
b111 .
b10000 2
1'
#906000
b101010 %
b101010 ,
b101010 3
b10000 2
b111 1
b1000 /
b111 -
b101011 &
b101011 +
b101011 8
0*
0!
b101010 4
0"
#910000
b1001 0
b1000 .
b10000 2
1"
1*
1!
0'
#911000
b101011 7
#915000
b1001 0
b1000 .
b10000 2
1'
#916000
b101011 %
b101011 ,
b101011 3
b10000 2
b1000 1
b1001 /
b1000 -
b101100 &
b101100 +
b101100 8
0*
0!
b101011 4
0"
#920000
b1010 0
b1001 .
b10000 2
1"
1*
1!
0'
#921000
b101100 7
#925000
b1010 0
b1001 .
b10000 2
1'
#926000
b101100 %
b101100 ,
b101100 3
b10000 2
b1001 1
b1010 /
b1001 -
b101101 &
b101101 +
b101101 8
0*
0!
b101100 4
0"
#930000
b1011 0
b1010 .
b10000 2
1"
1*
1!
0'
#931000
b101101 7
#935000
b1011 0
b1010 .
b10000 2
1'
#936000
b101101 %
b101101 ,
b101101 3
b10000 2
b1010 1
b1011 /
b1010 -
b101110 &
b101110 +
b101110 8
0*
0!
b101101 4
0"
#940000
b1100 0
b1011 .
b10000 2
1"
1*
1!
0'
#941000
b101110 7
#945000
b1100 0
b1011 .
b10000 2
1'
#946000
b101110 %
b101110 ,
b101110 3
b10000 2
b1011 1
b1100 /
b1011 -
b101111 &
b101111 +
b101111 8
0*
0!
b101110 4
0"
#950000
b1101 0
b1100 .
b10000 2
1"
1*
1!
0'
#951000
b101111 7
#955000
b1101 0
b1100 .
b10000 2
1'
#956000
b101111 %
b101111 ,
b101111 3
b10000 2
b1100 1
b1101 /
b1100 -
b110000 &
b110000 +
b110000 8
0*
0!
b101111 4
0"
#960000
b1110 0
b1101 .
b10000 2
1"
1*
1!
0'
#961000
b110000 7
#965000
b1110 0
b1101 .
b10000 2
1'
#966000
b110000 %
b110000 ,
b110000 3
b10000 2
b1101 1
b1110 /
b1101 -
b110001 &
b110001 +
b110001 8
0*
0!
b110000 4
0"
#970000
b1111 0
b10000 2
b1000 5
1*
1!
0'
#975000
b1111 0
b10000 2
1'
#976000
b10000 2
b1110 1
b1111 /
b110010 &
b110010 +
b110010 8
0*
0!
#980000
b10000 0
b10000 2
1*
1!
0'
#985000
b10000 0
b10000 2
1'
#986000
b10000 2
b1111 1
b10000 /
b110011 &
b110011 +
b110011 8
0*
0!
#990000
b101 9
0'
#995000
b10000 2
1'
#996000
b10000 1
#1000000
0'
#1005000
b10000 2
1'
#1010000
0'
#1015000
b10000 2
1'
#1020000
0'
#1025000
b10000 2
1'
#1030000
0'
#1035000
b10001 0
1*
1!
b10000 2
b1100 9
1'
#1040000
0'
#1045000
b1110 .
b10001 0
1"
b1101 5
b10000 2
1'
#1046000
b1110 .
b10000 2
b110001 7
b10001 /
b110100 &
b110100 +
b110100 8
0*
0!
#1050000
b10010 0
b1110 .
b10000 2
1*
1!
0'
#1055000
b10010 0
b1110 .
b10000 2
1'
#1056000
b110001 %
b110001 ,
b110001 3
b10000 2
b10001 1
b10010 /
b1110 -
b110001 4
0"
b110101 &
b110101 +
b110101 8
0*
0!
#1060000
b10011 0
b1111 .
b10000 2
1*
1!
1"
0'
#1061000
b110010 7
#1065000
b10011 0
b1111 .
b10000 2
1'
#1066000
b110010 %
b110010 ,
b110010 3
b10000 2
b10010 1
b10011 /
b1111 -
b110110 &
b110110 +
b110110 8
0*
0!
b110010 4
0"
#1070000
b10100 0
b10000 .
b10000 2
1"
1*
1!
0'
#1071000
b110011 7
#1075000
b10100 0
b10000 .
b10000 2
1'
#1076000
b110011 %
b110011 ,
b110011 3
b10000 2
b10011 1
b10100 /
b10000 -
b110111 &
b110111 +
b110111 8
0*
0!
b110011 4
0"
#1080000
b10101 0
b10001 .
b10000 2
1"
1*
1!
0'
#1081000
b110100 7
#1085000
b10101 0
b10001 .
b10000 2
1'
#1086000
b110100 %
b110100 ,
b110100 3
b10000 2
b10100 1
b10101 /
b10001 -
b111000 &
b111000 +
b111000 8
0*
0!
b110100 4
0"
#1090000
b10110 0
b10010 .
b10000 2
1"
1*
1!
0'
#1091000
b110101 7
#1095000
b10110 0
b10010 .
b10000 2
1'
#1096000
b110101 %
b110101 ,
b110101 3
b10000 2
b10101 1
b10110 /
b10010 -
b111001 &
b111001 +
b111001 8
0*
0!
b110101 4
0"
#1100000
b10111 0
b10011 .
b10000 2
1"
1*
1!
0'
#1101000
b110110 7
#1105000
b10111 0
b10011 .
b10000 2
1'
#1106000
b110110 %
b110110 ,
b110110 3
b10000 2
b10110 1
b10111 /
b10011 -
b111010 &
b111010 +
b111010 8
0*
0!
b110110 4
0"
#1110000
b11000 0
b10100 .
b10000 2
1"
1*
1!
0'
#1111000
b110111 7
#1115000
b11000 0
b10100 .
b10000 2
1'
#1116000
b110111 %
b110111 ,
b110111 3
b10000 2
b10111 1
b11000 /
b10100 -
b111011 &
b111011 +
b111011 8
0*
0!
b110111 4
0"
#1120000
b11001 0
b10101 .
b10000 2
1"
1*
1!
0'
#1121000
b111000 7
#1125000
b11001 0
b10101 .
b10000 2
1'
#1126000
b111000 %
b111000 ,
b111000 3
b10000 2
b11000 1
b11001 /
b10101 -
b111100 &
b111100 +
b111100 8
0*
0!
b111000 4
0"
#1130000
b11010 0
b10110 .
b10000 2
1"
1*
1!
0'
#1131000
b111001 7
#1135000
b11010 0
b10110 .
b10000 2
1'
#1136000
b111001 %
b111001 ,
b111001 3
b10000 2
b11001 1
b11010 /
b10110 -
b111101 &
b111101 +
b111101 8
0*
0!
b111001 4
0"
#1140000
b11011 0
b10111 .
b10000 2
1"
1*
1!
0'
#1141000
b111010 7
#1145000
b11011 0
b10111 .
b10000 2
1'
#1146000
b111010 %
b111010 ,
b111010 3
b10000 2
b11010 1
b11011 /
b10111 -
b111110 &
b111110 +
b111110 8
0*
0!
b111010 4
0"
#1150000
b11100 0
b11000 .
b10000 2
1"
1*
1!
0'
#1151000
b111011 7
#1155000
b11100 0
b11000 .
b10000 2
1'
#1156000
b111011 %
b111011 ,
b111011 3
b10000 2
b11011 1
b11100 /
b11000 -
b111111 &
b111111 +
b111111 8
0*
0!
b111011 4
0"
#1160000
b11001 .
b10000 2
b1101 9
1"
0'
#1161000
b111100 7
#1165000
b11001 .
b10000 2
1'
#1166000
b111100 %
b111100 ,
b111100 3
b10000 2
b11100 1
b11001 -
b111100 4
0"
#1170000
b11010 .
b10000 2
1"
0'
#1171000
b111101 7
#1175000
b11010 .
b10000 2
1'
#1176000
b111101 %
b111101 ,
b111101 3
b10000 2
b11010 -
b111101 4
0"
#1180000
b101 5
0'
#1185000
b10000 2
1'
#1190000
0'
#1195000
b10000 2
1'
#1200000
0'
#1205000
b10000 2
1'
#1210000
0'
#1215000
b10000 2
1'
#1220000
0'
#1225000
b11011 .
1"
b10000 2
b11 5
1'
#1226000
b111110 7
#1230000
0'
#1235000
b11011 .
b10000 2
1'
#1236000
b111110 %
b111110 ,
b111110 3
b10000 2
b11011 -
b111110 4
0"
#1240000
b11100 .
b10000 2
1"
0'
